{
	"easycom": {
		"^u-(.*)": "@/uview-ui/components/u-$1/u-$1.vue"
	},
	"pages": [ //
		{
			"path": "pages/index/index",
			"style": {
				"navigationBarTitleText": "index"
			}
		},
		{
			"path": "pages/page1/page1",
			"style": {
				"navigationBarTitleText": "page1"
			}
		},
		{
			"path": "pages/page2/page2",
			"style": {
				"navigationBarTitleText": "page2"
			}
		}
	],
	"globalStyle": {
		"navigationBarTextStyle": "black",
		"navigationBarTitleText": "uni-app",
		"navigationBarBackgroundColor": "#F8F8F8",
		"backgroundColor": "#F8F8F8"
	},
	"tabBar": {
		"color": "#7A7E83",
		"selectedColor": "#007AFF",
		"borderStyle": "black",
		"backgroundColor": "#F8F8F8",
		"list": [ //
			{
				"pagePath": "pages/index/index",
				"text": "index"
			},
			{
				"pagePath": "pages/page1/page1",
				"text": "page1"
			}, {
				"pagePath": "pages/page2/page2",
				"text": "page2"
			}
		]
	},
	"topWindow": {
		"path": "pages/topWindow"
	}
}
